{
  "ru": {
    "header_title": "UNION STONE",
    "header_subtitle": "откройте для себя янтарное чудо света",
    "nav_menu": "Меню",
    "nav_portfolio": "Портфолио",
    "nav_online_shop": "Онлайн магазин",
    "contacts_title": "поделиться страницей",
    "intro_title": "Union Stone — это единственные в мире изделия из камней янтаря.",
    "intro_description": "Ювелиры Union - это хранители вековых традицы, которые передавались из поколения в поколение и сегодня они первые, кто смогли в ручню объединить каждый камень янтаря, в одно целое. Благодрая изучению Арабских стран, Alessandro Rossti изобрел революционную формулу, которая позволила получить беспрецедентный материал с исключительными характеристиками, предельной контрастностью, цвета и тепла.",
    "intro_searchButton1": "Задолбать Серого",
    "intro_searchButton2": "Продолжить долбежку",
    "intro_searchButton3": "Задолбем вас",
    "intro_configurator": "Конфигуратор часов",
    "trends_title": "Сделайте свой дом уникальным",
    "trends_description": "Изучите современные тенденции и обставьте свой дом в соответствии со своими вкусами",
    "trends_item_1": "Жилые интерьеры",
    "trends_item_2": "Промышленность",
    "trends_item_3": "Архитектурное проэктирование",
    "trends_item_4": "Проекты сезона от UNION",
    "advertising_foreword": "Мир Rolex",
    "advertising_title": "Rolex и Открытый чемпионат Австралии",
    "advertising_button": "Подробнее",
    "about_foreword": "Многогранность Rolex",
    "about_first_story_title": "Секреты могучей реки Замбези ",
    "about_second_story_title": "Исследуя подземные пещеры",
    "about_third_story_title": "Следовать логике океана",
    "about_story_website": "Union.org",
    "": "",
    "": "",
    "": "",
    "footer_service_language": "Сменить язык"
  },



  "en": {
    "header_title": "UNION STONE",
    "header_subtitle": "discover the amber wonder of the world",
    "nav_menu": "Menu",
    "nav_portfolio": "Portfolio",
    "nav_online_shop": "Online shop",
    "contacts_title": "share this page",
    "intro_title": "Union Stone is the only amber stone product in the world.",
    "intro_description": "Union jewelers are the keepers of centuries-old traditions that have been passed down from generation to generation, and today they are the first to be able to combine each amber stone into one whole by hand. Thanks to the study of the Arab countries, Alessandro Rossti invented a revolutionary formula that allowed him to obtain an unprecedented material with exceptional characteristics, extreme contrast, color and warmth.",
    "intro_searchButton1": "Discover the collection",
    "intro_searchButton2": "Configurator",
    "intro_searchButton3": "More info",
    "intro_configurator": "Configure your watch",
    "trends_title": "Make your home unique",
    "trends_description": "Explore current trends and furnish your home according to your tastes",
    "trends_item_1": "Residential interiors",
    "trends_item_2": "Industry",
    "trends_item_3": "Architectural Engineering",
    "trends_item_4": "Projects of the season from UNION",
    "advertising_foreword": "World of Rolex",
    "advertising_title": "Rolex and the Australian Open",
    "advertising_button": "Discover more",
    "about_foreword": "Многогранность Rolex",
    "about_first_story_title": "Секреты могучей реки Замбези ",
    "about_second_story_title": "Исследуя подземные пещеры",
    "about_third_story_title": "Следовать логике океана",
    "about_story_website": "Rolex.org",
    "": "",
    "footer_service_language": "Change language"
  }
}